README.md
setup.py
imgcompare/__init__.py
imgcompare/imgcompare.py
imgcomparely.egg-info/PKG-INFO
imgcomparely.egg-info/SOURCES.txt
imgcomparely.egg-info/dependency_links.txt
imgcomparely.egg-info/requires.txt
imgcomparely.egg-info/top_level.txt