Metadata-Version: 1.1
Name: imgcomparely
Version: 0.1.0
Summary: compares two images get difference percentage
Home-page: https://github.com/Lynn0401/imgcompare
Author: lynn0401
Author-email: 15601602423@163.com
License: MIT
Download-URL: https://github.com/Lynn0401/imgcompare/0.1.0
Keywords: image,compare
Platform: UNKNOWN
